R/__init__.py
EasyDataR-1.0.dist-info/LICENSE
EasyDataR-1.0.dist-info/LICENSE.md
EasyDataR-1.0.dist-info/METADATA
EasyDataR-1.0.dist-info/WHEEL
EasyDataR-1.0.dist-info/top_level.txt
EasyDataR-1.0.dist-info/RECORD
