Metadata-Version: 2.1
Name: EasyDataR
Version: 1.0
Summary: EasyDataR is a unofficial R package to read in data from EasyData platform of the State Bank of Pakistan
Home-page: https://github.com/drateeb/EasyDataR
Author: Dr Ateeb Syed
Keywords: R,EasyData,EasyDataR
Classifier: Intended Audience :: Developers
Classifier: License :: OSI Approved :: MIT License
Classifier: Operating System :: OS Independent
Classifier: Programming Language :: Python
License-File: LICENSE
License-File: LICENSE.md
Requires-Dist: readme-md
Requires-Dist: rpy2
